ZtjRegistry.py
py_ztj_registry-0.0.4.dist-info/METADATA
py_ztj_registry-0.0.4.dist-info/WHEEL
py_ztj_registry-0.0.4.dist-info/top_level.txt
py_ztj_registry-0.0.4.dist-info/RECORD
