Metadata-Version: 2.1
Name: py-ztj-registry
Version: 0.0.4
Summary: python registry package
Home-page: https://github.com/ztj-package/py-registry
Author: ZhangTianJie
Author-email: ztj1993@gmail.com
License: MIT License
Keywords: registry config json yaml
Platform: UNKNOWN
